[
  {
    "id": "b310dc34-21e0-4da2-b07c-3081c1a3baa2",
    "customer_id": "8fd59b6c-6573-444b-a200-fab32ece4dc7",
    "event_type": null,
    "catering_type": null,
    "service_style": null,
    "venue_type": null,
    "guest_count": null,
    "event_date": null,
    "city": null,
    "postal_code": null,
    "budget_total": null,
    "budget_per_person": null,
    "planning_stage": null,
    "special_requests": null,
    "cuisine_preferences": [],
    "dietary_requirements": [],
    "extra_services": [],
    "status": "draft",
    "created_at": "2026-04-11T22:48:58.518271+00:00",
    "updated_at": "2026-04-11T22:48:58.518271+00:00",
    "ai_query": null,
    "lat": null,
    "lng": null,
    "preferred_caterer_id": null,
    "source": "speisely_marketplace",
    "storefront_slug": null,
    "_review_reason": "Unknown status: 'draft'",
    "_role": "Customer"
  },
  {
    "id": "c26ccf36-82d3-4e31-82e8-9e836431ecd7",
    "customer_id": "8fd59b6c-6573-444b-a200-fab32ece4dc7",
    "event_type": null,
    "catering_type": null,
    "service_style": null,
    "venue_type": null,
    "guest_count": null,
    "event_date": null,
    "city": null,
    "postal_code": null,
    "budget_total": null,
    "budget_per_person": null,
    "planning_stage": null,
    "special_requests": null,
    "cuisine_preferences": [],
    "dietary_requirements": [],
    "extra_services": [],
    "status": "draft",
    "created_at": "2026-04-11T22:55:44.324779+00:00",
    "updated_at": "2026-04-11T22:55:44.324779+00:00",
    "ai_query": null,
    "lat": null,
    "lng": null,
    "preferred_caterer_id": null,
    "source": "speisely_marketplace",
    "storefront_slug": null,
    "_review_reason": "Unknown status: 'draft'",
    "_role": "Customer"
  },
  {
    "id": "a23c998f-8c23-47fe-a008-6662ecea7b25",
    "customer_id": "8fd59b6c-6573-444b-a200-fab32ece4dc7",
    "event_type": null,
    "catering_type": null,
    "service_style": null,
    "venue_type": null,
    "guest_count": null,
    "event_date": null,
    "city": null,
    "postal_code": null,
    "budget_total": null,
    "budget_per_person": null,
    "planning_stage": null,
    "special_requests": null,
    "cuisine_preferences": [],
    "dietary_requirements": [],
    "extra_services": [],
    "status": "draft",
    "created_at": "2026-04-11T23:01:39.138627+00:00",
    "updated_at": "2026-04-11T23:01:39.138627+00:00",
    "ai_query": null,
    "lat": null,
    "lng": null,
    "preferred_caterer_id": null,
    "source": "speisely_marketplace",
    "storefront_slug": null,
    "_review_reason": "Unknown status: 'draft'",
    "_role": "Customer"
  },
  {
    "id": "7d6a98a1-d226-4b36-8ef4-ee09938f4389",
    "customer_id": "8fd59b6c-6573-444b-a200-fab32ece4dc7",
    "event_type": null,
    "catering_type": null,
    "service_style": null,
    "venue_type": null,
    "guest_count": null,
    "event_date": null,
    "city": null,
    "postal_code": null,
    "budget_total": null,
    "budget_per_person": null,
    "planning_stage": null,
    "special_requests": null,
    "cuisine_preferences": [],
    "dietary_requirements": [],
    "extra_services": [],
    "status": "draft",
    "created_at": "2026-04-11T23:05:13.715977+00:00",
    "updated_at": "2026-04-11T23:05:13.715977+00:00",
    "ai_query": null,
    "lat": null,
    "lng": null,
    "preferred_caterer_id": null,
    "source": "speisely_marketplace",
    "storefront_slug": null,
    "_review_reason": "Unknown status: 'draft'",
    "_role": "Customer"
  },
  {
    "id": "6735af17-80fd-425f-89e9-1ab72daaa6bd",
    "customer_id": "8fd59b6c-6573-444b-a200-fab32ece4dc7",
    "event_type": null,
    "catering_type": null,
    "service_style": null,
    "venue_type": null,
    "guest_count": null,
    "event_date": null,
    "city": null,
    "postal_code": null,
    "budget_total": null,
    "budget_per_person": null,
    "planning_stage": null,
    "special_requests": null,
    "cuisine_preferences": [],
    "dietary_requirements": [],
    "extra_services": [],
    "status": "draft",
    "created_at": "2026-04-11T23:06:27.445857+00:00",
    "updated_at": "2026-04-11T23:06:27.445857+00:00",
    "ai_query": null,
    "lat": null,
    "lng": null,
    "preferred_caterer_id": null,
    "source": "speisely_marketplace",
    "storefront_slug": null,
    "_review_reason": "Unknown status: 'draft'",
    "_role": "Customer"
  },
  {
    "id": "6b967215-d27c-422a-a79e-d359a1af35fe",
    "customer_id": "8fd59b6c-6573-444b-a200-fab32ece4dc7",
    "event_type": null,
    "catering_type": null,
    "service_style": null,
    "venue_type": null,
    "guest_count": null,
    "event_date": null,
    "city": null,
    "postal_code": null,
    "budget_total": null,
    "budget_per_person": null,
    "planning_stage": null,
    "special_requests": null,
    "cuisine_preferences": [],
    "dietary_requirements": [],
    "extra_services": [],
    "status": "draft",
    "created_at": "2026-04-11T23:09:15.323869+00:00",
    "updated_at": "2026-04-11T23:09:15.323869+00:00",
    "ai_query": null,
    "lat": null,
    "lng": null,
    "preferred_caterer_id": null,
    "source": "speisely_marketplace",
    "storefront_slug": null,
    "_review_reason": "Unknown status: 'draft'",
    "_role": "Customer"
  },
  {
    "id": "19f0e54e-bb57-4783-9e81-9fa3f8c1cc8b",
    "customer_id": "8fd59b6c-6573-444b-a200-fab32ece4dc7",
    "event_type": null,
    "catering_type": null,
    "service_style": null,
    "venue_type": null,
    "guest_count": null,
    "event_date": null,
    "city": null,
    "postal_code": null,
    "budget_total": null,
    "budget_per_person": null,
    "planning_stage": null,
    "special_requests": null,
    "cuisine_preferences": [],
    "dietary_requirements": [],
    "extra_services": [],
    "status": "draft",
    "created_at": "2026-04-17T12:48:17.470045+00:00",
    "updated_at": "2026-04-17T12:48:17.470045+00:00",
    "ai_query": null,
    "lat": null,
    "lng": null,
    "preferred_caterer_id": null,
    "source": "speisely_marketplace",
    "storefront_slug": null,
    "_review_reason": "Unknown status: 'draft'",
    "_role": "Customer"
  },
  {
    "id": "0bc19e14-4a01-47c4-b5c2-fb7d95aa1f56",
    "customer_id": "8fd59b6c-6573-444b-a200-fab32ece4dc7",
    "event_type": "birthday",
    "catering_type": "finger_food",
    "service_style": null,
    "venue_type": null,
    "guest_count": 50,
    "event_date": null,
    "city": "Mülheim an der Ruhr",
    "postal_code": "45473",
    "budget_total": null,
    "budget_per_person": null,
    "planning_stage": null,
    "special_requests": null,
    "cuisine_preferences": [],
    "dietary_requirements": [],
    "extra_services": [],
    "status": "draft",
    "created_at": "2026-04-11T23:12:13.712711+00:00",
    "updated_at": "2026-04-11T23:15:52.945427+00:00",
    "ai_query": null,
    "lat": null,
    "lng": null,
    "preferred_caterer_id": null,
    "source": "speisely_marketplace",
    "storefront_slug": null,
    "_review_reason": "Unknown status: 'draft'",
    "_role": "Customer"
  },
  {
    "id": "c9a6a63b-3182-4b49-839c-46f2722865a2",
    "customer_id": "8fd59b6c-6573-444b-a200-fab32ece4dc7",
    "event_type": "wedding",
    "catering_type": "buffet",
    "service_style": null,
    "venue_type": null,
    "guest_count": 67,
    "event_date": null,
    "city": "Berlin",
    "postal_code": "12681",
    "budget_total": null,
    "budget_per_person": null,
    "planning_stage": null,
    "special_requests": null,
    "cuisine_preferences": [],
    "dietary_requirements": [],
    "extra_services": [],
    "status": "draft",
    "created_at": "2026-04-11T23:30:00.659791+00:00",
    "updated_at": "2026-04-11T23:30:17.102041+00:00",
    "ai_query": null,
    "lat": null,
    "lng": null,
    "preferred_caterer_id": null,
    "source": "speisely_marketplace",
    "storefront_slug": null,
    "_review_reason": "Unknown status: 'draft'",
    "_role": "Customer"
  },
  {
    "id": "db4b0a51-78f6-4589-bc03-f91f26d94be5",
    "customer_id": "8fd59b6c-6573-444b-a200-fab32ece4dc7",
    "event_type": "birthday",
    "catering_type": "plated",
    "service_style": "full_service",
    "venue_type": null,
    "guest_count": 45,
    "event_date": null,
    "city": "Berlin",
    "postal_code": "12681",
    "budget_total": null,
    "budget_per_person": null,
    "planning_stage": null,
    "special_requests": null,
    "cuisine_preferences": [
      "Turkish"
    ],
    "dietary_requirements": [
      "Halal"
    ],
    "extra_services": [
      "Staff"
    ],
    "status": "draft",
    "created_at": "2026-04-11T23:33:24.67786+00:00",
    "updated_at": "2026-04-11T23:33:58.17207+00:00",
    "ai_query": null,
    "lat": null,
    "lng": null,
    "preferred_caterer_id": null,
    "source": "speisely_marketplace",
    "storefront_slug": null,
    "_review_reason": "Unknown status: 'draft'",
    "_role": "Customer"
  },
  {
    "id": "c2d53209-652d-423b-8742-7febd0132263",
    "customer_id": "8fd59b6c-6573-444b-a200-fab32ece4dc7",
    "event_type": "wedding",
    "catering_type": "finger_food",
    "service_style": "full_service",
    "venue_type": null,
    "guest_count": 56,
    "event_date": null,
    "city": "Berlin",
    "postal_code": "12681",
    "budget_total": null,
    "budget_per_person": null,
    "planning_stage": null,
    "special_requests": null,
    "cuisine_preferences": [
      "Italian",
      "Arabic"
    ],
    "dietary_requirements": [
      "Halal",
      "Vegetarian",
      "Gluten-free"
    ],
    "extra_services": [
      "Drinks",
      "Staff"
    ],
    "status": "draft",
    "created_at": "2026-04-11T23:36:53.879606+00:00",
    "updated_at": "2026-04-11T23:37:18.421346+00:00",
    "ai_query": null,
    "lat": null,
    "lng": null,
    "preferred_caterer_id": null,
    "source": "speisely_marketplace",
    "storefront_slug": null,
    "_review_reason": "Unknown status: 'draft'",
    "_role": "Customer"
  },
  {
    "id": "810ca6b2-12e6-4923-bf17-aa372af2a77e",
    "customer_id": "8fd59b6c-6573-444b-a200-fab32ece4dc7",
    "event_type": "wedding",
    "catering_type": "buffet",
    "service_style": "full_service",
    "venue_type": null,
    "guest_count": 33,
    "event_date": "2026-04-30",
    "city": "Berlin",
    "postal_code": "12681",
    "budget_total": 5000,
    "budget_per_person": null,
    "planning_stage": null,
    "special_requests": null,
    "cuisine_preferences": [
      "Arabic"
    ],
    "dietary_requirements": [
      "Vegetarian"
    ],
    "extra_services": [
      "Setup & Cleanup"
    ],
    "status": "draft",
    "created_at": "2026-04-11T23:41:01.969907+00:00",
    "updated_at": "2026-04-11T23:41:40.043362+00:00",
    "ai_query": null,
    "lat": null,
    "lng": null,
    "preferred_caterer_id": null,
    "source": "speisely_marketplace",
    "storefront_slug": null,
    "_review_reason": "Unknown status: 'draft'",
    "_role": "Customer"
  },
  {
    "id": "e13ab16d-ce55-447f-9a1d-a59b45e0e17d",
    "customer_id": "8fd59b6c-6573-444b-a200-fab32ece4dc7",
    "event_type": null,
    "catering_type": null,
    "service_style": null,
    "venue_type": null,
    "guest_count": null,
    "event_date": null,
    "city": null,
    "postal_code": null,
    "budget_total": null,
    "budget_per_person": null,
    "planning_stage": null,
    "special_requests": null,
    "cuisine_preferences": [],
    "dietary_requirements": [],
    "extra_services": [],
    "status": "draft",
    "created_at": "2026-04-11T23:59:56.92284+00:00",
    "updated_at": "2026-04-11T23:59:56.92284+00:00",
    "ai_query": null,
    "lat": null,
    "lng": null,
    "preferred_caterer_id": null,
    "source": "speisely_marketplace",
    "storefront_slug": null,
    "_review_reason": "Unknown status: 'draft'",
    "_role": "Customer"
  },
  {
    "id": "363ad260-7b16-4de9-8749-673f91c3202d",
    "customer_id": "8fd59b6c-6573-444b-a200-fab32ece4dc7",
    "event_type": null,
    "catering_type": null,
    "service_style": null,
    "venue_type": null,
    "guest_count": null,
    "event_date": null,
    "city": null,
    "postal_code": null,
    "budget_total": null,
    "budget_per_person": null,
    "planning_stage": null,
    "special_requests": null,
    "cuisine_preferences": [],
    "dietary_requirements": [],
    "extra_services": [],
    "status": "draft",
    "created_at": "2026-04-12T21:31:41.338356+00:00",
    "updated_at": "2026-04-12T21:31:41.338356+00:00",
    "ai_query": null,
    "lat": null,
    "lng": null,
    "preferred_caterer_id": null,
    "source": "speisely_marketplace",
    "storefront_slug": null,
    "_review_reason": "Unknown status: 'draft'",
    "_role": "Customer"
  },
  {
    "id": "e67382ee-c1e8-44ed-9f2c-9810b98d13e5",
    "customer_id": "8fd59b6c-6573-444b-a200-fab32ece4dc7",
    "event_type": null,
    "catering_type": null,
    "service_style": null,
    "venue_type": null,
    "guest_count": null,
    "event_date": null,
    "city": null,
    "postal_code": null,
    "budget_total": null,
    "budget_per_person": null,
    "planning_stage": null,
    "special_requests": null,
    "cuisine_preferences": [],
    "dietary_requirements": [],
    "extra_services": [],
    "status": "draft",
    "created_at": "2026-04-12T21:32:22.484777+00:00",
    "updated_at": "2026-04-12T21:32:22.484777+00:00",
    "ai_query": null,
    "lat": null,
    "lng": null,
    "preferred_caterer_id": null,
    "source": "speisely_marketplace",
    "storefront_slug": null,
    "_review_reason": "Unknown status: 'draft'",
    "_role": "Customer"
  },
  {
    "id": "53a4d8f4-3c7b-4e22-b65c-fe4ed4db9325",
    "customer_id": "8fd59b6c-6573-444b-a200-fab32ece4dc7",
    "event_type": null,
    "catering_type": null,
    "service_style": null,
    "venue_type": null,
    "guest_count": null,
    "event_date": null,
    "city": null,
    "postal_code": null,
    "budget_total": null,
    "budget_per_person": null,
    "planning_stage": null,
    "special_requests": null,
    "cuisine_preferences": [],
    "dietary_requirements": [],
    "extra_services": [],
    "status": "draft",
    "created_at": "2026-04-17T12:47:58.564356+00:00",
    "updated_at": "2026-04-17T12:47:58.564356+00:00",
    "ai_query": null,
    "lat": null,
    "lng": null,
    "preferred_caterer_id": null,
    "source": "speisely_marketplace",
    "storefront_slug": null,
    "_review_reason": "Unknown status: 'draft'",
    "_role": "Customer"
  },
  {
    "id": "8026052e-fded-43a6-b7a4-126adbc0bdad",
    "customer_id": "8fd59b6c-6573-444b-a200-fab32ece4dc7",
    "event_type": null,
    "catering_type": null,
    "service_style": null,
    "venue_type": null,
    "guest_count": null,
    "event_date": null,
    "city": null,
    "postal_code": null,
    "budget_total": null,
    "budget_per_person": null,
    "planning_stage": null,
    "special_requests": null,
    "cuisine_preferences": [],
    "dietary_requirements": [],
    "extra_services": [],
    "status": "draft",
    "created_at": "2026-04-17T12:47:58.564361+00:00",
    "updated_at": "2026-04-17T12:47:58.564361+00:00",
    "ai_query": null,
    "lat": null,
    "lng": null,
    "preferred_caterer_id": null,
    "source": "speisely_marketplace",
    "storefront_slug": null,
    "_review_reason": "Unknown status: 'draft'",
    "_role": "Customer"
  },
  {
    "id": "02e42760-9a0a-4f84-86c9-fcd24173d419",
    "customer_id": "8fd59b6c-6573-444b-a200-fab32ece4dc7",
    "event_type": null,
    "catering_type": null,
    "service_style": null,
    "venue_type": null,
    "guest_count": null,
    "event_date": null,
    "city": null,
    "postal_code": null,
    "budget_total": null,
    "budget_per_person": null,
    "planning_stage": null,
    "special_requests": null,
    "cuisine_preferences": [],
    "dietary_requirements": [],
    "extra_services": [],
    "status": "draft",
    "created_at": "2026-04-17T12:47:59.78783+00:00",
    "updated_at": "2026-04-17T12:47:59.78783+00:00",
    "ai_query": null,
    "lat": null,
    "lng": null,
    "preferred_caterer_id": null,
    "source": "speisely_marketplace",
    "storefront_slug": null,
    "_review_reason": "Unknown status: 'draft'",
    "_role": "Customer"
  },
  {
    "id": "336d2794-0d52-407c-8065-14bba0709b6a",
    "customer_id": "8fd59b6c-6573-444b-a200-fab32ece4dc7",
    "event_type": null,
    "catering_type": null,
    "service_style": null,
    "venue_type": null,
    "guest_count": null,
    "event_date": null,
    "city": null,
    "postal_code": null,
    "budget_total": null,
    "budget_per_person": null,
    "planning_stage": null,
    "special_requests": null,
    "cuisine_preferences": [],
    "dietary_requirements": [],
    "extra_services": [],
    "status": "draft",
    "created_at": "2026-04-17T12:48:01.896258+00:00",
    "updated_at": "2026-04-17T12:48:01.896258+00:00",
    "ai_query": null,
    "lat": null,
    "lng": null,
    "preferred_caterer_id": null,
    "source": "speisely_marketplace",
    "storefront_slug": null,
    "_review_reason": "Unknown status: 'draft'",
    "_role": "Customer"
  },
  {
    "id": "1b92b253-fce6-4e05-a20d-98227643741a",
    "customer_id": "8fd59b6c-6573-444b-a200-fab32ece4dc7",
    "event_type": null,
    "catering_type": null,
    "service_style": null,
    "venue_type": null,
    "guest_count": null,
    "event_date": null,
    "city": null,
    "postal_code": null,
    "budget_total": null,
    "budget_per_person": null,
    "planning_stage": null,
    "special_requests": null,
    "cuisine_preferences": [],
    "dietary_requirements": [],
    "extra_services": [],
    "status": "draft",
    "created_at": "2026-04-17T12:48:02.825012+00:00",
    "updated_at": "2026-04-17T12:48:02.825012+00:00",
    "ai_query": null,
    "lat": null,
    "lng": null,
    "preferred_caterer_id": null,
    "source": "speisely_marketplace",
    "storefront_slug": null,
    "_review_reason": "Unknown status: 'draft'",
    "_role": "Customer"
  },
  {
    "id": "8d089477-0ab8-4b29-b5b7-7c23483b7342",
    "customer_id": "8fd59b6c-6573-444b-a200-fab32ece4dc7",
    "event_type": null,
    "catering_type": null,
    "service_style": null,
    "venue_type": null,
    "guest_count": null,
    "event_date": null,
    "city": null,
    "postal_code": null,
    "budget_total": null,
    "budget_per_person": null,
    "planning_stage": null,
    "special_requests": null,
    "cuisine_preferences": [],
    "dietary_requirements": [],
    "extra_services": [],
    "status": "draft",
    "created_at": "2026-04-17T12:48:02.749061+00:00",
    "updated_at": "2026-04-17T12:48:02.749061+00:00",
    "ai_query": null,
    "lat": null,
    "lng": null,
    "preferred_caterer_id": null,
    "source": "speisely_marketplace",
    "storefront_slug": null,
    "_review_reason": "Unknown status: 'draft'",
    "_role": "Customer"
  },
  {
    "id": "92fd0dd5-65da-4d55-8cd2-afbd93227f50",
    "customer_id": "8fd59b6c-6573-444b-a200-fab32ece4dc7",
    "event_type": null,
    "catering_type": null,
    "service_style": null,
    "venue_type": null,
    "guest_count": null,
    "event_date": null,
    "city": null,
    "postal_code": null,
    "budget_total": null,
    "budget_per_person": null,
    "planning_stage": null,
    "special_requests": null,
    "cuisine_preferences": [],
    "dietary_requirements": [],
    "extra_services": [],
    "status": "draft",
    "created_at": "2026-04-17T12:48:02.911843+00:00",
    "updated_at": "2026-04-17T12:48:02.911843+00:00",
    "ai_query": null,
    "lat": null,
    "lng": null,
    "preferred_caterer_id": null,
    "source": "speisely_marketplace",
    "storefront_slug": null,
    "_review_reason": "Unknown status: 'draft'",
    "_role": "Customer"
  },
  {
    "id": "7cda6413-7ca6-40b0-b207-9fcb4aadc857",
    "customer_id": "8fd59b6c-6573-444b-a200-fab32ece4dc7",
    "event_type": null,
    "catering_type": null,
    "service_style": null,
    "venue_type": null,
    "guest_count": null,
    "event_date": null,
    "city": null,
    "postal_code": null,
    "budget_total": null,
    "budget_per_person": null,
    "planning_stage": null,
    "special_requests": null,
    "cuisine_preferences": [],
    "dietary_requirements": [],
    "extra_services": [],
    "status": "draft",
    "created_at": "2026-04-17T12:48:03.134398+00:00",
    "updated_at": "2026-04-17T12:48:03.134398+00:00",
    "ai_query": null,
    "lat": null,
    "lng": null,
    "preferred_caterer_id": null,
    "source": "speisely_marketplace",
    "storefront_slug": null,
    "_review_reason": "Unknown status: 'draft'",
    "_role": "Customer"
  },
  {
    "id": "558a2378-6e6d-42c2-80e9-81e28671e13c",
    "customer_id": "8fd59b6c-6573-444b-a200-fab32ece4dc7",
    "event_type": null,
    "catering_type": null,
    "service_style": null,
    "venue_type": null,
    "guest_count": null,
    "event_date": null,
    "city": null,
    "postal_code": null,
    "budget_total": null,
    "budget_per_person": null,
    "planning_stage": null,
    "special_requests": null,
    "cuisine_preferences": [],
    "dietary_requirements": [],
    "extra_services": [],
    "status": "draft",
    "created_at": "2026-04-17T12:48:03.25948+00:00",
    "updated_at": "2026-04-17T12:48:03.25948+00:00",
    "ai_query": null,
    "lat": null,
    "lng": null,
    "preferred_caterer_id": null,
    "source": "speisely_marketplace",
    "storefront_slug": null,
    "_review_reason": "Unknown status: 'draft'",
    "_role": "Customer"
  },
  {
    "id": "4846c493-6a09-490f-8710-da8804cc8c1e",
    "customer_id": "8fd59b6c-6573-444b-a200-fab32ece4dc7",
    "event_type": null,
    "catering_type": null,
    "service_style": null,
    "venue_type": null,
    "guest_count": null,
    "event_date": null,
    "city": null,
    "postal_code": null,
    "budget_total": null,
    "budget_per_person": null,
    "planning_stage": null,
    "special_requests": null,
    "cuisine_preferences": [],
    "dietary_requirements": [],
    "extra_services": [],
    "status": "draft",
    "created_at": "2026-04-17T12:48:03.552598+00:00",
    "updated_at": "2026-04-17T12:48:03.552598+00:00",
    "ai_query": null,
    "lat": null,
    "lng": null,
    "preferred_caterer_id": null,
    "source": "speisely_marketplace",
    "storefront_slug": null,
    "_review_reason": "Unknown status: 'draft'",
    "_role": "Customer"
  },
  {
    "id": "799e06e5-685f-4326-aa88-7ec191549b34",
    "customer_id": "8fd59b6c-6573-444b-a200-fab32ece4dc7",
    "event_type": "corporate",
    "catering_type": null,
    "service_style": null,
    "venue_type": null,
    "guest_count": null,
    "event_date": null,
    "city": null,
    "postal_code": null,
    "budget_total": null,
    "budget_per_person": null,
    "planning_stage": null,
    "special_requests": "Office Lunch für 40 Personen",
    "cuisine_preferences": [],
    "dietary_requirements": [],
    "extra_services": [],
    "status": "draft",
    "created_at": "2026-04-22T08:03:35.921923+00:00",
    "updated_at": "2026-04-22T08:03:35.921923+00:00",
    "ai_query": null,
    "lat": null,
    "lng": null,
    "preferred_caterer_id": null,
    "source": "speisely_marketplace",
    "storefront_slug": null,
    "_review_reason": "Unknown status: 'draft'",
    "_role": "Customer"
  },
  {
    "id": "1ee730f3-d694-4a3d-82f1-daa6575f3489",
    "customer_id": "8fd59b6c-6573-444b-a200-fab32ece4dc7",
    "event_type": "corporate",
    "catering_type": "buffet",
    "service_style": null,
    "venue_type": null,
    "guest_count": 45,
    "event_date": null,
    "city": "Berlin",
    "postal_code": "10115",
    "budget_total": null,
    "budget_per_person": 30,
    "planning_stage": null,
    "special_requests": "Business lunch for 45 people in Berlin, modern buffet, vegetarian options, about €30 per person",
    "cuisine_preferences": [],
    "dietary_requirements": [
      "Vegetarian"
    ],
    "extra_services": [],
    "status": "draft",
    "created_at": "2026-04-28T14:53:14.46435+00:00",
    "updated_at": "2026-04-28T14:53:14.46435+00:00",
    "ai_query": "Business lunch for 45 people in Berlin, modern buffet, vegetarian options, about €30 per person",
    "lat": 52.5337069545604,
    "lng": 13.387223860255,
    "preferred_caterer_id": null,
    "source": "speisely_marketplace",
    "storefront_slug": null,
    "_review_reason": "Unknown status: 'draft'",
    "_role": "Customer"
  },
  {
    "id": "d3706282-3be1-475f-8b1a-654470d8b2b6",
    "customer_id": "07dbf4b5-605d-4b7a-bd1b-d478b04b3895",
    "event_type": "wedding",
    "catering_type": "buffet",
    "service_style": "elegant",
    "venue_type": null,
    "guest_count": 80,
    "event_date": null,
    "city": "Berlin",
    "postal_code": "10115",
    "budget_total": null,
    "budget_per_person": 45,
    "planning_stage": null,
    "special_requests": "Hochzeit für 80 Gäste, vegetarisch, elegantes Buffet, ca. €45 pro Person",
    "cuisine_preferences": [],
    "dietary_requirements": [
      "Vegetarian"
    ],
    "extra_services": [],
    "status": "draft",
    "created_at": "2026-04-28T00:48:16.508206+00:00",
    "updated_at": "2026-04-28T00:48:16.508206+00:00",
    "ai_query": "Hochzeit für 80 Gäste, vegetarisch, elegantes Buffet, ca. €45 pro Person",
    "lat": 52.5337069545604,
    "lng": 13.387223860255,
    "preferred_caterer_id": null,
    "source": "speisely_marketplace",
    "storefront_slug": null,
    "_review_reason": "Unknown status: 'draft'",
    "_role": "Customer"
  },
  {
    "id": "e1686cd8-3c2b-4535-b00f-f94bfcc168a1",
    "customer_id": "8fd59b6c-6573-444b-a200-fab32ece4dc7",
    "event_type": "wedding",
    "catering_type": "buffet",
    "service_style": "elegant",
    "venue_type": null,
    "guest_count": 80,
    "event_date": null,
    "city": "Berlin",
    "postal_code": "10115",
    "budget_total": null,
    "budget_per_person": 45,
    "planning_stage": null,
    "special_requests": "Hochzeit für 80 Gäste, vegetarisch, elegantes Buffet, ca. €45 pro Person",
    "cuisine_preferences": [],
    "dietary_requirements": [
      "Vegetarian"
    ],
    "extra_services": [],
    "status": "draft",
    "created_at": "2026-04-27T22:18:14.024741+00:00",
    "updated_at": "2026-04-27T22:18:14.024741+00:00",
    "ai_query": "Hochzeit für 80 Gäste, vegetarisch, elegantes Buffet, ca. €45 pro Person",
    "lat": 52.5337069545604,
    "lng": 13.387223860255,
    "preferred_caterer_id": null,
    "source": "speisely_marketplace",
    "storefront_slug": null,
    "_review_reason": "Unknown status: 'draft'",
    "_role": "Customer"
  },
  {
    "id": "c7fee7c9-2e38-49c0-b35a-0ac1ddef898a",
    "customer_id": "07dbf4b5-605d-4b7a-bd1b-d478b04b3895",
    "event_type": "wedding",
    "catering_type": "buffet",
    "service_style": "elegant",
    "venue_type": null,
    "guest_count": 80,
    "event_date": null,
    "city": "Berlin",
    "postal_code": "10115",
    "budget_total": null,
    "budget_per_person": 45,
    "planning_stage": null,
    "special_requests": "Hochzeit für 80 Gäste, vegetarisch, elegantes Buffet, ca. €45 pro Person",
    "cuisine_preferences": [],
    "dietary_requirements": [
      "Vegetarian"
    ],
    "extra_services": [],
    "status": "draft",
    "created_at": "2026-04-28T09:48:48.869904+00:00",
    "updated_at": "2026-04-28T09:48:48.869904+00:00",
    "ai_query": "Hochzeit für 80 Gäste, vegetarisch, elegantes Buffet, ca. €45 pro Person",
    "lat": 52.5337069545604,
    "lng": 13.387223860255,
    "preferred_caterer_id": null,
    "source": "speisely_marketplace",
    "storefront_slug": null,
    "_review_reason": "Unknown status: 'draft'",
    "_role": "Customer"
  },
  {
    "id": "a42a2e43-2de2-417b-b664-82bfcd8b82be",
    "customer_id": "07dbf4b5-605d-4b7a-bd1b-d478b04b3895",
    "event_type": "wedding",
    "catering_type": "buffet",
    "service_style": "elegant",
    "venue_type": null,
    "guest_count": 80,
    "event_date": null,
    "city": "Berlin",
    "postal_code": "10115",
    "budget_total": null,
    "budget_per_person": 45,
    "planning_stage": null,
    "special_requests": "Hochzeit für 80 Gäste, vegetarisch, elegantes Buffet, ca. €45 pro Person",
    "cuisine_preferences": [],
    "dietary_requirements": [
      "Vegetarian"
    ],
    "extra_services": [],
    "status": "draft",
    "created_at": "2026-04-28T09:49:51.430948+00:00",
    "updated_at": "2026-04-28T09:49:51.430948+00:00",
    "ai_query": "Hochzeit für 80 Gäste, vegetarisch, elegantes Buffet, ca. €45 pro Person",
    "lat": 52.5337069545604,
    "lng": 13.387223860255,
    "preferred_caterer_id": null,
    "source": "speisely_marketplace",
    "storefront_slug": null,
    "_review_reason": "Unknown status: 'draft'",
    "_role": "Customer"
  },
  {
    "id": "9a5e462a-e020-4dc5-ae35-6e362b18f9e7",
    "customer_id": "8fd59b6c-6573-444b-a200-fab32ece4dc7",
    "event_type": "wedding",
    "catering_type": "buffet",
    "service_style": "elegant",
    "venue_type": null,
    "guest_count": 80,
    "event_date": null,
    "city": "Berlin",
    "postal_code": "10115",
    "budget_total": null,
    "budget_per_person": 45,
    "planning_stage": null,
    "special_requests": "Wedding for 80 guests in Berlin, vegetarian, elegant buffet, about €45 per person",
    "cuisine_preferences": [],
    "dietary_requirements": [
      "Vegetarian"
    ],
    "extra_services": [],
    "status": "draft",
    "created_at": "2026-04-28T14:34:46.904494+00:00",
    "updated_at": "2026-04-28T14:34:46.904494+00:00",
    "ai_query": "Wedding for 80 guests in Berlin, vegetarian, elegant buffet, about €45 per person",
    "lat": 52.5337069545604,
    "lng": 13.387223860255,
    "preferred_caterer_id": null,
    "source": "speisely_marketplace",
    "storefront_slug": null,
    "_review_reason": "Unknown status: 'draft'",
    "_role": "Customer"
  },
  {
    "id": "4e62ce5a-c94d-47a0-a69b-cfd52ece44fd",
    "customer_id": "8fd59b6c-6573-444b-a200-fab32ece4dc7",
    "event_type": "wedding",
    "catering_type": "buffet",
    "service_style": "elegant",
    "venue_type": null,
    "guest_count": 80,
    "event_date": null,
    "city": "Berlin",
    "postal_code": "10115",
    "budget_total": null,
    "budget_per_person": 45,
    "planning_stage": null,
    "special_requests": "Wedding for 80 guests in Berlin, vegetarian, elegant buffet, about €45 per person",
    "cuisine_preferences": [],
    "dietary_requirements": [
      "Vegetarian"
    ],
    "extra_services": [],
    "status": "draft",
    "created_at": "2026-04-28T14:51:38.641662+00:00",
    "updated_at": "2026-04-28T14:51:38.641662+00:00",
    "ai_query": "Wedding for 80 guests in Berlin, vegetarian, elegant buffet, about €45 per person",
    "lat": 52.5337069545604,
    "lng": 13.387223860255,
    "preferred_caterer_id": null,
    "source": "speisely_marketplace",
    "storefront_slug": null,
    "_review_reason": "Unknown status: 'draft'",
    "_role": "Customer"
  },
  {
    "id": "884cc649-d91e-4fde-a92e-f50f452daabb",
    "customer_id": "8fd59b6c-6573-444b-a200-fab32ece4dc7",
    "event_type": "wedding",
    "catering_type": "buffet",
    "service_style": "elegant",
    "venue_type": null,
    "guest_count": 80,
    "event_date": null,
    "city": "Berlin",
    "postal_code": "10115",
    "budget_total": null,
    "budget_per_person": 45,
    "planning_stage": null,
    "special_requests": "Wedding for 80 guests in Berlin, vegetarian, elegant buffet, about €45 per person",
    "cuisine_preferences": [],
    "dietary_requirements": [
      "Vegetarian"
    ],
    "extra_services": [],
    "status": "draft",
    "created_at": "2026-04-28T15:45:07.632621+00:00",
    "updated_at": "2026-04-28T15:45:07.632621+00:00",
    "ai_query": "Wedding for 80 guests in Berlin, vegetarian, elegant buffet, about €45 per person",
    "lat": 52.5337069545604,
    "lng": 13.387223860255,
    "preferred_caterer_id": null,
    "source": "speisely_marketplace",
    "storefront_slug": null,
    "_review_reason": "Unknown status: 'draft'",
    "_role": "Customer"
  },
  {
    "id": "6978e417-ff2e-4e4b-9680-b055f0af7fb1",
    "customer_id": "8fd59b6c-6573-444b-a200-fab32ece4dc7",
    "event_type": "wedding",
    "catering_type": null,
    "service_style": null,
    "venue_type": null,
    "guest_count": 80,
    "event_date": null,
    "city": "frankfurt",
    "postal_code": null,
    "budget_total": null,
    "budget_per_person": null,
    "planning_stage": null,
    "special_requests": "80 guest wedding frankfurt",
    "cuisine_preferences": [],
    "dietary_requirements": [],
    "extra_services": [],
    "status": "draft",
    "created_at": "2026-04-29T08:21:29.410581+00:00",
    "updated_at": "2026-04-29T08:21:29.410581+00:00",
    "ai_query": "80 guest wedding frankfurt",
    "lat": null,
    "lng": null,
    "preferred_caterer_id": null,
    "source": "speisely_marketplace",
    "storefront_slug": null,
    "_review_reason": "Unknown status: 'draft'",
    "_role": "Customer"
  },
  {
    "id": "1afeb253-dc15-4d0f-aef6-fa91dda63916",
    "customer_id": "8fd59b6c-6573-444b-a200-fab32ece4dc7",
    "event_type": "wedding",
    "catering_type": "buffet",
    "service_style": "elegant",
    "venue_type": null,
    "guest_count": 80,
    "event_date": null,
    "city": "Berlin",
    "postal_code": null,
    "budget_total": null,
    "budget_per_person": 45,
    "planning_stage": null,
    "special_requests": "Wedding for 80 guests in Berlin, vegetarian, elegant buffet, about €45 per person",
    "cuisine_preferences": [],
    "dietary_requirements": [
      "Vegetarian"
    ],
    "extra_services": [],
    "status": "draft",
    "created_at": "2026-04-29T08:21:47.073042+00:00",
    "updated_at": "2026-04-29T08:21:47.073042+00:00",
    "ai_query": "Wedding for 80 guests in Berlin, vegetarian, elegant buffet, about €45 per person",
    "lat": null,
    "lng": null,
    "preferred_caterer_id": null,
    "source": "speisely_marketplace",
    "storefront_slug": null,
    "_review_reason": "Unknown status: 'draft'",
    "_role": "Customer"
  },
  {
    "id": "c597a86f-f852-4004-82cd-ad5363e61629",
    "customer_id": "8fd59b6c-6573-444b-a200-fab32ece4dc7",
    "event_type": null,
    "catering_type": null,
    "service_style": null,
    "venue_type": null,
    "guest_count": 45,
    "event_date": null,
    "city": "leipzig",
    "postal_code": null,
    "budget_total": null,
    "budget_per_person": null,
    "planning_stage": null,
    "special_requests": "45 people gathering in leipzig for birthdapart at 30 july 2026",
    "cuisine_preferences": [],
    "dietary_requirements": [],
    "extra_services": [],
    "status": "draft",
    "created_at": "2026-04-29T08:40:12.147934+00:00",
    "updated_at": "2026-04-29T08:40:12.147934+00:00",
    "ai_query": "45 people gathering in leipzig for birthdapart at 30 july 2026",
    "lat": null,
    "lng": null,
    "preferred_caterer_id": null,
    "source": "speisely_marketplace",
    "storefront_slug": null,
    "_review_reason": "Unknown status: 'draft'",
    "_role": "Customer"
  },
  {
    "id": "45229244-829c-4a3f-877c-d74c916ec4b5",
    "customer_id": "8fd59b6c-6573-444b-a200-fab32ece4dc7",
    "event_type": "birthday",
    "catering_type": "plated",
    "service_style": "fine dining",
    "venue_type": null,
    "guest_count": 65,
    "event_date": null,
    "city": "Dresden",
    "postal_code": null,
    "budget_total": null,
    "budget_per_person": 45,
    "planning_stage": null,
    "special_requests": "Birthday party for 65 guests in Dresden, fine dining, €45 per person",
    "cuisine_preferences": [
      "Fine Dining"
    ],
    "dietary_requirements": [],
    "extra_services": [],
    "status": "draft",
    "created_at": "2026-04-29T09:15:22.515259+00:00",
    "updated_at": "2026-04-29T09:15:22.515259+00:00",
    "ai_query": "Birthday party for 65 guests in Dresden, fine dining, €45 per person",
    "lat": null,
    "lng": null,
    "preferred_caterer_id": null,
    "source": "speisely_marketplace",
    "storefront_slug": null,
    "_review_reason": "Unknown status: 'draft'",
    "_role": "Customer"
  },
  {
    "id": "b04009c7-dae0-4d30-b842-40bf174bcc61",
    "customer_id": "8fd59b6c-6573-444b-a200-fab32ece4dc7",
    "event_type": "wedding",
    "catering_type": "buffet",
    "service_style": "elegant",
    "venue_type": null,
    "guest_count": 80,
    "event_date": null,
    "city": "Berlin",
    "postal_code": null,
    "budget_total": null,
    "budget_per_person": 45,
    "planning_stage": null,
    "special_requests": "Wedding for 80 guests in Berlin, vegetarian, elegant buffet, about €45 per person",
    "cuisine_preferences": [],
    "dietary_requirements": [
      "Vegetarian"
    ],
    "extra_services": [],
    "status": "draft",
    "created_at": "2026-04-29T09:16:23.399695+00:00",
    "updated_at": "2026-04-29T09:16:23.399695+00:00",
    "ai_query": "Wedding for 80 guests in Berlin, vegetarian, elegant buffet, about €45 per person",
    "lat": null,
    "lng": null,
    "preferred_caterer_id": null,
    "source": "speisely_marketplace",
    "storefront_slug": null,
    "_review_reason": "Unknown status: 'draft'",
    "_role": "Customer"
  },
  {
    "id": "01fbc4ef-c8da-4974-8431-9660cc55e1e4",
    "customer_id": "8fd59b6c-6573-444b-a200-fab32ece4dc7",
    "event_type": "wedding",
    "catering_type": "buffet",
    "service_style": "elegant",
    "venue_type": null,
    "guest_count": 75,
    "event_date": null,
    "city": "Berlin",
    "postal_code": null,
    "budget_total": null,
    "budget_per_person": 45,
    "planning_stage": null,
    "special_requests": "Hochzeit für 75 Gäste in Berlin, vegetarisch, elegantes Buffet, €45 p.P.",
    "cuisine_preferences": [],
    "dietary_requirements": [
      "Vegetarian"
    ],
    "extra_services": [],
    "status": "draft",
    "created_at": "2026-04-29T11:10:22.526787+00:00",
    "updated_at": "2026-04-29T11:10:22.526787+00:00",
    "ai_query": "Hochzeit für 75 Gäste in Berlin, vegetarisch, elegantes Buffet, €45 p.P.",
    "lat": null,
    "lng": null,
    "preferred_caterer_id": null,
    "source": "speisely_marketplace",
    "storefront_slug": null,
    "_review_reason": "Unknown status: 'draft'",
    "_role": "Customer"
  },
  {
    "id": "635c7161-2d2e-4c44-a6b7-d5974a87f979",
    "customer_id": "8fd59b6c-6573-444b-a200-fab32ece4dc7",
    "event_type": "wedding",
    "catering_type": "buffet",
    "service_style": "elegant",
    "venue_type": null,
    "guest_count": 80,
    "event_date": null,
    "city": "Berlin",
    "postal_code": null,
    "budget_total": null,
    "budget_per_person": 45,
    "planning_stage": null,
    "special_requests": "Wedding for 80 guests in Berlin, vegetarian, elegant buffet, about €45 per person",
    "cuisine_preferences": [],
    "dietary_requirements": [
      "Vegetarian"
    ],
    "extra_services": [],
    "status": "draft",
    "created_at": "2026-04-29T11:11:49.165214+00:00",
    "updated_at": "2026-04-29T11:11:49.165214+00:00",
    "ai_query": "Wedding for 80 guests in Berlin, vegetarian, elegant buffet, about €45 per person",
    "lat": null,
    "lng": null,
    "preferred_caterer_id": null,
    "source": "speisely_marketplace",
    "storefront_slug": null,
    "_review_reason": "Unknown status: 'draft'",
    "_role": "Customer"
  },
  {
    "id": "638152dd-a078-4dfc-a64b-c1c521e9abe3",
    "customer_id": "8fd59b6c-6573-444b-a200-fab32ece4dc7",
    "event_type": "corporate",
    "catering_type": "buffet",
    "service_style": null,
    "venue_type": null,
    "guest_count": 45,
    "event_date": null,
    "city": "Berlin",
    "postal_code": null,
    "budget_total": null,
    "budget_per_person": 30,
    "planning_stage": null,
    "special_requests": "Business lunch for 45 people in Berlin, modern buffet, vegetarian options, about €30 per person",
    "cuisine_preferences": [],
    "dietary_requirements": [
      "Vegetarian"
    ],
    "extra_services": [],
    "status": "draft",
    "created_at": "2026-04-29T11:12:33.209633+00:00",
    "updated_at": "2026-04-29T11:12:33.209633+00:00",
    "ai_query": "Business lunch for 45 people in Berlin, modern buffet, vegetarian options, about €30 per person",
    "lat": null,
    "lng": null,
    "preferred_caterer_id": null,
    "source": "speisely_marketplace",
    "storefront_slug": null,
    "_review_reason": "Unknown status: 'draft'",
    "_role": "Customer"
  },
  {
    "id": "34e4b489-98b3-4548-9068-88b932d5cb76",
    "customer_id": "8fd59b6c-6573-444b-a200-fab32ece4dc7",
    "event_type": "wedding",
    "catering_type": "buffet",
    "service_style": "elegant",
    "venue_type": null,
    "guest_count": 80,
    "event_date": null,
    "city": "Berlin",
    "postal_code": null,
    "budget_total": null,
    "budget_per_person": 45,
    "planning_stage": null,
    "special_requests": "Wedding for 80 guests in Berlin, vegetarian, elegant buffet, about €45 per person",
    "cuisine_preferences": [],
    "dietary_requirements": [
      "Vegetarian"
    ],
    "extra_services": [],
    "status": "draft",
    "created_at": "2026-04-29T11:13:11.173268+00:00",
    "updated_at": "2026-04-29T11:13:11.173268+00:00",
    "ai_query": "Wedding for 80 guests in Berlin, vegetarian, elegant buffet, about €45 per person",
    "lat": null,
    "lng": null,
    "preferred_caterer_id": null,
    "source": "speisely_marketplace",
    "storefront_slug": null,
    "_review_reason": "Unknown status: 'draft'",
    "_role": "Customer"
  },
  {
    "id": "f72c90a5-0cbc-4adc-a0be-1beaa86d8d68",
    "customer_id": "8fd59b6c-6573-444b-a200-fab32ece4dc7",
    "event_type": "wedding",
    "catering_type": "buffet",
    "service_style": "elegant",
    "venue_type": null,
    "guest_count": 80,
    "event_date": null,
    "city": "Berlin",
    "postal_code": null,
    "budget_total": null,
    "budget_per_person": 45,
    "planning_stage": null,
    "special_requests": "Wedding for 80 guests in Berlin, vegetarian, elegant buffet, about €45 per person",
    "cuisine_preferences": [],
    "dietary_requirements": [
      "Vegetarian"
    ],
    "extra_services": [],
    "status": "draft",
    "created_at": "2026-04-29T11:34:44.182534+00:00",
    "updated_at": "2026-04-29T11:34:44.182534+00:00",
    "ai_query": "Wedding for 80 guests in Berlin, vegetarian, elegant buffet, about €45 per person",
    "lat": null,
    "lng": null,
    "preferred_caterer_id": null,
    "source": "speisely_marketplace",
    "storefront_slug": null,
    "_review_reason": "Unknown status: 'draft'",
    "_role": "Customer"
  },
  {
    "id": "ed6089b5-ce13-461c-8769-746c931c8f2f",
    "customer_id": "8fd59b6c-6573-444b-a200-fab32ece4dc7",
    "event_type": "corporate",
    "catering_type": "buffet",
    "service_style": null,
    "venue_type": null,
    "guest_count": 45,
    "event_date": null,
    "city": "Berlin",
    "postal_code": null,
    "budget_total": null,
    "budget_per_person": 30,
    "planning_stage": null,
    "special_requests": "Business Lunch für 45 Personen in Berlin, modernes Buffet, vegetarische Optionen, ca. €30 pro Person",
    "cuisine_preferences": [],
    "dietary_requirements": [
      "Vegetarian"
    ],
    "extra_services": [],
    "status": "draft",
    "created_at": "2026-04-29T11:48:42.80519+00:00",
    "updated_at": "2026-04-29T11:48:42.80519+00:00",
    "ai_query": "Business Lunch für 45 Personen in Berlin, modernes Buffet, vegetarische Optionen, ca. €30 pro Person",
    "lat": null,
    "lng": null,
    "preferred_caterer_id": null,
    "source": "speisely_marketplace",
    "storefront_slug": null,
    "_review_reason": "Unknown status: 'draft'",
    "_role": "Customer"
  },
  {
    "id": "582cfbc7-3558-44ff-94f5-81a3c5768f1d",
    "customer_id": "8fd59b6c-6573-444b-a200-fab32ece4dc7",
    "event_type": "wedding",
    "catering_type": "buffet",
    "service_style": "elegant",
    "venue_type": null,
    "guest_count": 80,
    "event_date": null,
    "city": "Berlin",
    "postal_code": null,
    "budget_total": null,
    "budget_per_person": 45,
    "planning_stage": null,
    "special_requests": "Hochzeit für 80 Gäste in Berlin, vegetarisch, elegantes Buffet, €45 p.P.",
    "cuisine_preferences": [],
    "dietary_requirements": [
      "Vegetarian"
    ],
    "extra_services": [],
    "status": "draft",
    "created_at": "2026-05-01T12:17:21.360539+00:00",
    "updated_at": "2026-05-01T12:17:21.360539+00:00",
    "ai_query": "Hochzeit für 80 Gäste in Berlin, vegetarisch, elegantes Buffet, €45 p.P.",
    "lat": null,
    "lng": null,
    "preferred_caterer_id": null,
    "source": "speisely_marketplace",
    "storefront_slug": null,
    "_review_reason": "Unknown status: 'draft'",
    "_role": "Customer"
  },
  {
    "id": "e1b4cd51-647d-4727-8969-d8ba587edfa7",
    "customer_id": "8fd59b6c-6573-444b-a200-fab32ece4dc7",
    "event_type": "wedding",
    "catering_type": "buffet",
    "service_style": "elegant",
    "venue_type": null,
    "guest_count": 80,
    "event_date": null,
    "city": "Berlin",
    "postal_code": null,
    "budget_total": null,
    "budget_per_person": 45,
    "planning_stage": null,
    "special_requests": "Hochzeit für 80 Gäste in Berlin, vegetarisch, elegantes Buffet, €45 p.P.",
    "cuisine_preferences": [],
    "dietary_requirements": [
      "Vegetarian"
    ],
    "extra_services": [],
    "status": "draft",
    "created_at": "2026-05-01T12:17:37.061231+00:00",
    "updated_at": "2026-05-01T12:17:37.061231+00:00",
    "ai_query": "Hochzeit für 80 Gäste in Berlin, vegetarisch, elegantes Buffet, €45 p.P.",
    "lat": null,
    "lng": null,
    "preferred_caterer_id": null,
    "source": "speisely_marketplace",
    "storefront_slug": null,
    "_review_reason": "Unknown status: 'draft'",
    "_role": "Customer"
  },
  {
    "id": "310c95a5-61f0-41d7-8148-829edb6155a2",
    "customer_id": "8fd59b6c-6573-444b-a200-fab32ece4dc7",
    "event_type": "birthday",
    "catering_type": null,
    "service_style": null,
    "venue_type": null,
    "guest_count": 20,
    "event_date": null,
    "city": "Berlin",
    "postal_code": null,
    "budget_total": null,
    "budget_per_person": null,
    "planning_stage": null,
    "special_requests": "Im.looking to host a birthday of my son with 20 guests in house",
    "cuisine_preferences": [],
    "dietary_requirements": [],
    "extra_services": [],
    "status": "draft",
    "created_at": "2026-05-01T12:18:29.112286+00:00",
    "updated_at": "2026-05-01T12:18:29.112286+00:00",
    "ai_query": "Im.looking to host a birthday of my son with 20 guests in house",
    "lat": null,
    "lng": null,
    "preferred_caterer_id": null,
    "source": "speisely_marketplace",
    "storefront_slug": null,
    "_review_reason": "Unknown status: 'draft'",
    "_role": "Customer"
  },
  {
    "id": "585ff472-0a32-43a3-a02e-8984428ef470",
    "customer_id": "8fd59b6c-6573-444b-a200-fab32ece4dc7",
    "event_type": "private_party",
    "catering_type": null,
    "service_style": null,
    "venue_type": null,
    "guest_count": 20,
    "event_date": null,
    "city": "Berlin",
    "postal_code": null,
    "budget_total": null,
    "budget_per_person": null,
    "planning_stage": null,
    "special_requests": "birhtday party for 20 people in berlin",
    "cuisine_preferences": [],
    "dietary_requirements": [],
    "extra_services": [],
    "status": "draft",
    "created_at": "2026-05-03T14:50:44.139072+00:00",
    "updated_at": "2026-05-03T14:50:44.139072+00:00",
    "ai_query": "birhtday party for 20 people in berlin",
    "lat": null,
    "lng": null,
    "preferred_caterer_id": null,
    "source": "speisely_marketplace",
    "storefront_slug": null,
    "_review_reason": "Unknown status: 'draft'",
    "_role": "Customer"
  },
  {
    "id": "b489c870-c9c7-4c01-83e4-09b0b7e97a33",
    "customer_id": "8fd59b6c-6573-444b-a200-fab32ece4dc7",
    "event_type": "private_party",
    "catering_type": null,
    "service_style": null,
    "venue_type": null,
    "guest_count": 80,
    "event_date": null,
    "city": "Berlin",
    "postal_code": null,
    "budget_total": null,
    "budget_per_person": null,
    "planning_stage": null,
    "special_requests": "birtdayparty o´for 80 guest in berlin",
    "cuisine_preferences": [],
    "dietary_requirements": [],
    "extra_services": [],
    "status": "draft",
    "created_at": "2026-05-03T14:57:11.70366+00:00",
    "updated_at": "2026-05-03T14:57:11.70366+00:00",
    "ai_query": "birtdayparty o´for 80 guest in berlin",
    "lat": null,
    "lng": null,
    "preferred_caterer_id": null,
    "source": "speisely_marketplace",
    "storefront_slug": null,
    "_review_reason": "Unknown status: 'draft'",
    "_role": "Customer"
  },
  {
    "id": "79eefe5f-55ff-4272-926a-b20b437c84b0",
    "customer_id": "8fd59b6c-6573-444b-a200-fab32ece4dc7",
    "event_type": "wedding",
    "catering_type": "buffet",
    "service_style": "elegant",
    "venue_type": null,
    "guest_count": 80,
    "event_date": null,
    "city": "Berlin",
    "postal_code": null,
    "budget_total": null,
    "budget_per_person": 45,
    "planning_stage": null,
    "special_requests": "Hochzeit für 80 Gäste in Berlin, vegetarisch, elegantes Buffet, €45 p.P.",
    "cuisine_preferences": [],
    "dietary_requirements": [
      "Vegetarian"
    ],
    "extra_services": [],
    "status": "draft",
    "created_at": "2026-05-03T15:03:14.00156+00:00",
    "updated_at": "2026-05-03T15:03:14.00156+00:00",
    "ai_query": "Hochzeit für 80 Gäste in Berlin, vegetarisch, elegantes Buffet, €45 p.P.",
    "lat": null,
    "lng": null,
    "preferred_caterer_id": null,
    "source": "speisely_marketplace",
    "storefront_slug": null,
    "_review_reason": "Unknown status: 'draft'",
    "_role": "Customer"
  },
  {
    "id": "83759f3a-f205-4e08-9230-e966f9f50ae6",
    "customer_id": "8fd59b6c-6573-444b-a200-fab32ece4dc7",
    "event_type": "wedding",
    "catering_type": "buffet",
    "service_style": "elegant",
    "venue_type": null,
    "guest_count": 80,
    "event_date": null,
    "city": "Berlin",
    "postal_code": null,
    "budget_total": null,
    "budget_per_person": 45,
    "planning_stage": null,
    "special_requests": "Hochzeit für 80 Gäste in Berlin, vegetarisch, elegantes Buffet, ca. €45 pro Person",
    "cuisine_preferences": [],
    "dietary_requirements": [
      "Vegetarian"
    ],
    "extra_services": [],
    "status": "draft",
    "created_at": "2026-05-03T15:03:58.388307+00:00",
    "updated_at": "2026-05-03T15:03:58.388307+00:00",
    "ai_query": "Hochzeit für 80 Gäste in Berlin, vegetarisch, elegantes Buffet, ca. €45 pro Person",
    "lat": null,
    "lng": null,
    "preferred_caterer_id": null,
    "source": "speisely_marketplace",
    "storefront_slug": null,
    "_review_reason": "Unknown status: 'draft'",
    "_role": "Customer"
  }
]